odoo/addons/product_assortment_description/README.rst
odoo/addons/product_assortment_description/__init__.py
odoo/addons/product_assortment_description/__manifest__.py
odoo/addons/product_assortment_description/i18n/product_assortment_description.pot
odoo/addons/product_assortment_description/models/__init__.py
odoo/addons/product_assortment_description/models/ir_filters.py
odoo/addons/product_assortment_description/readme/CONTRIBUTORS.rst
odoo/addons/product_assortment_description/readme/DESCRIPTION.rst
odoo/addons/product_assortment_description/readme/HISTORY.rst
odoo/addons/product_assortment_description/readme/USAGE.rst
odoo/addons/product_assortment_description/static/description/icon.png
odoo/addons/product_assortment_description/static/description/index.html
odoo/addons/product_assortment_description/views/product_assortment.xml
odoo14_addon_product_assortment_description-14.0.1.0.1.dist-info/METADATA
odoo14_addon_product_assortment_description-14.0.1.0.1.dist-info/WHEEL
odoo14_addon_product_assortment_description-14.0.1.0.1.dist-info/top_level.txt
odoo14_addon_product_assortment_description-14.0.1.0.1.dist-info/RECORD
